eprice_pkg/__init__.py
eprice_pkg_ZeroAutumn-0.0.1.dist-info/LICENCE
eprice_pkg_ZeroAutumn-0.0.1.dist-info/METADATA
eprice_pkg_ZeroAutumn-0.0.1.dist-info/WHEEL
eprice_pkg_ZeroAutumn-0.0.1.dist-info/top_level.txt
eprice_pkg_ZeroAutumn-0.0.1.dist-info/RECORD
